pysequila/__init__.py
pysequila/sequila.py
pysequila/tests/__init__.py
pysequila-0.4.1.dist-info/LICENSE
pysequila-0.4.1.dist-info/METADATA
pysequila-0.4.1.dist-info/WHEEL
pysequila-0.4.1.dist-info/top_level.txt
pysequila-0.4.1.dist-info/RECORD
