Metadata-Version: 2.1
Name: pysequila
Version: 0.4.1
Summary: An SQL-based solution for large-scale genomic analysis
Home-page: https://biodatageeks.github.io/sequila/
Author: biodatageeks
Author-email: team@biodatageeks.org
Classifier: Development Status :: 5 - Production/Stable
Classifier: Intended Audience :: Developers
Classifier: License :: OSI Approved :: Apache Software License
Classifier: Programming Language :: Python
Classifier: Programming Language :: Python :: 3
Classifier: Programming Language :: Python :: 3.8
Classifier: Programming Language :: Python :: 3.9
Classifier: Programming Language :: Python :: Implementation :: CPython
Classifier: Programming Language :: Python :: Implementation :: PyPy
License-File: LICENSE
Requires-Dist: setuptools
Requires-Dist: typeguard (==2.9.1)
Requires-Dist: pyspark (==3.2.2)
Requires-Dist: findspark
Requires-Dist: pandas
Provides-Extra: rest
Requires-Dist: Sphinx ; extra == 'rest'
